capiscio/__init__.py
capiscio/cli.py
capiscio/manager.py
capiscio-2.3.1.dist-info/METADATA
capiscio-2.3.1.dist-info/WHEEL
capiscio-2.3.1.dist-info/entry_points.txt
capiscio-2.3.1.dist-info/licenses/LICENSE
capiscio-2.3.1.dist-info/RECORD
