Metadata-Version: 2.4
Name: capiscio
Version: 2.3.1
Summary: The official CapiscIO CLI tool for validating A2A agents.
Project-URL: Homepage, https://capisc.io
Project-URL: Documentation, https://docs.capisc.io/cli
Project-URL: Repository, https://github.com/capiscio/capiscio-python
Project-URL: Issues, https://github.com/capiscio/capiscio-python/issues
Author-email: Capiscio Team <team@capisc.io>
License: Apache-2.0
License-File: LICENSE
Keywords: a2a,agent,capiscio,cli,tool,validation
Classifier: Development Status :: 3 - Alpha
Classifier: Intended Audience :: Developers
Classifier: License :: OSI Approved :: Apache Software License
Classifier: Programming Language :: Python :: 3
Classifier: Programming Language :: Python :: 3.10
Classifier: Programming Language :: Python :: 3.11
Classifier: Programming Language :: Python :: 3.12
Classifier: Topic :: Software Development :: Quality Assurance
Classifier: Topic :: Utilities
Requires-Python: >=3.10
Requires-Dist: platformdirs>=4.0.0
Requires-Dist: requests>=2.31.0
Requires-Dist: rich>=13.0.0
Provides-Extra: dev
Requires-Dist: build; extra == 'dev'
Requires-Dist: pytest>=7.0.0; extra == 'dev'
Requires-Dist: twine; extra == 'dev'
Provides-Extra: test
Requires-Dist: pytest-cov>=4.0.0; extra == 'test'
Requires-Dist: pytest>=7.0.0; extra == 'test'
Requires-Dist: requests>=2.31.0; extra == 'test'
